{
  "exclusion_flow": {
    "total_delivery_rows": 58848,
    "ent_delivery_rows": 18704,
    "total_rw_list": 268,
    "single_staff_facilities": 105,
    "ent_rw_doctors": 230,
    "total_viewing_rows": 12559,
    "viewing_after_filter": 2955,
    "total_doctors": 214,
    "total_facilities": 158,
    "multi_staff_facilities": 95,
    "multi_fac_doctors": 16,
    "clean_pairs": 67,
    "washout_excluded": 2,
    "late_excluded": 2,
    "final_treated": 41,
    "final_control": 22,
    "final_total": 63
  },
  "excluded_ids": {
    "washout": [
      "D0051",
      "D0090"
    ],
    "multi_fac": [
      "D0028",
      "D0038",
      "D0084",
      "D0135",
      "D0139",
      "D0144",
      "D0160",
      "D0177",
      "D0185",
      "D0205",
      "D0207",
      "D0242",
      "D0272",
      "D0287",
      "D0300",
      "D0304"
    ],
    "late": [
      "D0049",
      "D0092"
    ]
  },
  "twfe": {
    "att": 30.168712333300885,
    "se": 4.146450787690536,
    "p": 3.443945828885781e-13,
    "ci_lo": 22.041818125759697,
    "ci_hi": 38.29560654084207,
    "sig": "***"
  },
  "twfe_robust": {
    "att": 30.17370022550223,
    "se": 4.148363918720343,
    "p": 3.4993121495938683e-13,
    "ci_lo": 22.043056350044914,
    "ci_hi": 38.30434410095955,
    "sig": "***",
    "mr_activity_coef": 0.11140522144760329,
    "mr_activity_se": 0.6108929328459294,
    "mr_activity_p": 0.8552966357337024,
    "mr_activity_sig": "n.s.",
    "att_change_pct": 0.01653332812564161,
    "covariates": [
      "mr_activity_count"
    ]
  },
  "cs_overall": {
    "att": 35.378896103896096,
    "se": 4.983487217631704,
    "p": 1.2545520178264269e-12,
    "ci_lo": 25.611261157337957,
    "ci_hi": 45.146531050454236,
    "sig": "***",
    "dynamic": [
      {
        "event_time": -6,
        "att": -4.896853146853146,
        "se": 4.305875183773477,
        "ci_lo": -13.336368507049158,
        "ci_hi": 3.542662213342868
      },
      {
        "event_time": -5,
        "att": -1.0696969696969698,
        "se": 4.4085289556199605,
        "ci_lo": -9.710413722712092,
        "ci_hi": 7.571019783318151
      },
      {
        "event_time": -4,
        "att": -6.979946524064169,
        "se": 3.6848174939584073,
        "ci_lo": -14.202188812222648,
        "ci_hi": 0.24229576409430909
      },
      {
        "event_time": -3,
        "att": -6.831339712918661,
        "se": 3.9286098914703165,
        "ci_lo": -14.53141510020048,
        "ci_hi": 0.8687356743631591
      },
      {
        "event_time": -2,
        "att": 0.9567627494456754,
        "se": 4.4644936986679955,
        "ci_lo": -7.793644899943595,
        "ci_hi": 9.707170398834945
      },
      {
        "event_time": -1,
        "att": 0.0,
        "se": 0.0,
        "ci_lo": 0.0,
        "ci_hi": 0.0
      },
      {
        "event_time": 0,
        "att": 13.866962305986695,
        "se": 4.491536915524529,
        "ci_lo": 5.063549951558619,
        "ci_hi": 22.670374660414772
      },
      {
        "event_time": 1,
        "att": 24.546563192904657,
        "se": 4.29021815153371,
        "ci_lo": 16.137735615898585,
        "ci_hi": 32.95539076991073
      },
      {
        "event_time": 2,
        "att": 20.647450110864742,
        "se": 4.866090951045701,
        "ci_lo": 11.10991184681517,
        "ci_hi": 30.184988374914315
      },
      {
        "event_time": 3,
        "att": 22.736141906873616,
        "se": 4.904511623615407,
        "ci_lo": 13.123299124587419,
        "ci_hi": 32.34898468915981
      },
      {
        "event_time": 4,
        "att": 22.735033259423503,
        "se": 4.403406898267312,
        "ci_lo": 14.104355738819573,
        "ci_hi": 31.365710780027435
      },
      {
        "event_time": 5,
        "att": 24.99334811529933,
        "se": 5.1266511704345055,
        "ci_lo": 14.9451118212477,
        "ci_hi": 35.04158440935096
      },
      {
        "event_time": 6,
        "att": 28.98558758314856,
        "se": 6.522389197436498,
        "ci_lo": 16.201704756173026,
        "ci_hi": 41.7694704101241
      },
      {
        "event_time": 7,
        "att": 30.248337028824828,
        "se": 5.116251130503099,
        "ci_lo": 20.220484813038752,
        "ci_hi": 40.276189244610904
      },
      {
        "event_time": 8,
        "att": 34.74833702882483,
        "se": 5.208941557959349,
        "ci_lo": 24.538811575224504,
        "ci_hi": 44.957862482425156
      },
      {
        "event_time": 9,
        "att": 32.793791574279375,
        "se": 5.33625473515571,
        "ci_lo": 22.334732293374184,
        "ci_hi": 43.25285085518456
      },
      {
        "event_time": 10,
        "att": 36.10643015521064,
        "se": 6.489371011967793,
        "ci_lo": 23.387262971753763,
        "ci_hi": 48.825597338667514
      },
      {
        "event_time": 11,
        "att": 37.25942350332594,
        "se": 6.176990181593455,
        "ci_lo": 25.15252274740277,
        "ci_hi": 49.36632425924911
      },
      {
        "event_time": 12,
        "att": 43.00113636363636,
        "se": 6.401958398092994,
        "ci_lo": 30.453297903374093,
        "ci_hi": 55.54897482389863
      },
      {
        "event_time": 13,
        "att": 48.10909090909091,
        "se": 6.730888279829479,
        "ci_lo": 34.91654988062513,
        "ci_hi": 61.301631937556685
      },
      {
        "event_time": 14,
        "att": 45.87878787878788,
        "se": 6.932718895946571,
        "ci_lo": 32.290658842732604,
        "ci_hi": 59.46691691484316
      },
      {
        "event_time": 15,
        "att": 44.306526806526804,
        "se": 6.427699518091669,
        "ci_lo": 31.708235751067136,
        "ci_hi": 56.90481786198647
      },
      {
        "event_time": 16,
        "att": 34.3120393120393,
        "se": 6.792530732919002,
        "ci_lo": 20.99867907551806,
        "ci_hi": 47.62539954856055
      },
      {
        "event_time": 17,
        "att": 45.81684491978609,
        "se": 7.877298703402563,
        "ci_lo": 30.377339461117067,
        "ci_hi": 61.25635037845512
      },
      {
        "event_time": 18,
        "att": 44.62700534759358,
        "se": 7.342760540189069,
        "ci_lo": 30.235194688823007,
        "ci_hi": 59.018816006364155
      }
    ]
  },
  "cs_channel": {
    "Webinar": {
      "att": 35.733001762780155,
      "se": 5.636747594873701,
      "p": 2.3082002975627347e-10,
      "ci_lo": 24.6849764768277,
      "ci_hi": 46.78102704873261,
      "sig": "***",
      "n_treated": 32,
      "dynamic": [
        {
          "event_time": -6,
          "att": -9.109848484848483,
          "se": 6.2410940731850975,
          "ci_lo": -21.342392868291274,
          "ci_hi": 3.1226958985943085
        },
        {
          "event_time": -5,
          "att": -7.298951048951046,
          "se": 6.110077966222969,
          "ci_lo": -19.274703862748066,
          "ci_hi": 4.676801764845973
        },
        {
          "event_time": -4,
          "att": -6.326018808777428,
          "se": 4.6102034424092695,
          "ci_lo": -15.362017555899595,
          "ci_hi": 2.7099799383447403
        },
        {
          "event_time": -3,
          "att": -0.8870967741935479,
          "se": 4.266736386624406,
          "ci_lo": -9.249900091977384,
          "ci_hi": 7.475706543590288
        },
        {
          "event_time": -2,
          "att": 1.9531250000000027,
          "se": 4.8348625356504575,
          "ci_lo": -7.523205569874894,
          "ci_hi": 11.4294555698749
        },
        {
          "event_time": -1,
          "att": 0.0,
          "se": 0.0,
          "ci_lo": 0.0,
          "ci_hi": 0.0
        },
        {
          "event_time": 0,
          "att": 22.34659090909091,
          "se": 5.147681187394051,
          "ci_lo": 12.25713578179857,
          "ci_hi": 32.436046036383246
        },
        {
          "event_time": 1,
          "att": 28.29971590909091,
          "se": 5.263993086195935,
          "ci_lo": 17.98228946014688,
          "ci_hi": 38.61714235803494
        },
        {
          "event_time": 2,
          "att": 27.484375000000007,
          "se": 4.628119808092292,
          "ci_lo": 18.413260176139115,
          "ci_hi": 36.555489823860896
        },
        {
          "event_time": 3,
          "att": 29.575284090909093,
          "se": 5.799348048385299,
          "ci_lo": 18.208561916073908,
          "ci_hi": 40.94200626574428
        },
        {
          "event_time": 4,
          "att": 33.77840909090909,
          "se": 4.598952566132658,
          "ci_lo": 24.764462061289084,
          "ci_hi": 42.79235612052911
        },
        {
          "event_time": 5,
          "att": 30.667613636363633,
          "se": 5.301233501436344,
          "ci_lo": 20.2771959735484,
          "ci_hi": 41.058031299178865
        },
        {
          "event_time": 6,
          "att": 35.37642045454545,
          "se": 6.213810770237535,
          "ci_lo": 23.197351344879884,
          "ci_hi": 47.55548956421102
        },
        {
          "event_time": 7,
          "att": 36.41051136363636,
          "se": 5.469667134042966,
          "ci_lo": 25.689963780912144,
          "ci_hi": 47.131058946360575
        },
        {
          "event_time": 8,
          "att": 37.02414772727273,
          "se": 6.202602479368614,
          "ci_lo": 24.867046867710243,
          "ci_hi": 49.18124858683521
        },
        {
          "event_time": 9,
          "att": 43.559659090909086,
          "se": 5.5456972589308435,
          "ci_lo": 32.69009246340463,
          "ci_hi": 54.42922571841354
        },
        {
          "event_time": 10,
          "att": 40.37642045454545,
          "se": 6.322319189441014,
          "ci_lo": 27.984674843241066,
          "ci_hi": 52.76816606584984
        },
        {
          "event_time": 11,
          "att": 40.991477272727266,
          "se": 6.259036611799873,
          "ci_lo": 28.723765513599517,
          "ci_hi": 53.259189031855016
        },
        {
          "event_time": 12,
          "att": 39.946022727272734,
          "se": 6.339238654271046,
          "ci_lo": 27.521114964901486,
          "ci_hi": 52.37093048964398
        },
        {
          "event_time": 13,
          "att": 43.44176136363636,
          "se": 7.782109281088065,
          "ci_lo": 28.188827172703753,
          "ci_hi": 58.694695554568966
        },
        {
          "event_time": 14,
          "att": 42.128787878787875,
          "se": 7.140047552668753,
          "ci_lo": 28.134294675557122,
          "ci_hi": 56.12328108201863
        },
        {
          "event_time": 15,
          "att": 43.24090909090909,
          "se": 8.01631106415761,
          "ci_lo": 27.528939405160173,
          "ci_hi": 58.95287877665801
        },
        {
          "event_time": 16,
          "att": 37.75,
          "se": 7.566289340323029,
          "ci_lo": 22.920072892966864,
          "ci_hi": 52.579927107033136
        },
        {
          "event_time": 17,
          "att": 40.46153846153846,
          "se": 8.619205989547153,
          "ci_lo": 23.56789472202604,
          "ci_hi": 57.35518220105088
        },
        {
          "event_time": 18,
          "att": 36.54545454545454,
          "se": 8.696706371056312,
          "ci_lo": 19.49991005818417,
          "ci_hi": 53.59099903272491
        }
      ]
    },
    "e-contents": {
      "att": 30.67823202438587,
      "se": 7.418026033672691,
      "p": 3.539777829342228e-05,
      "ci_lo": 16.1389009983874,
      "ci_hi": 45.21756305038434,
      "sig": "***",
      "n_treated": 23,
      "dynamic": [
        {
          "event_time": -6,
          "att": -2.3522727272727257,
          "se": 8.979975228935254,
          "ci_lo": -19.953024175985824,
          "ci_hi": 15.248478721440371
        },
        {
          "event_time": -5,
          "att": -2.985645933014355,
          "se": 6.682651545253626,
          "ci_lo": -16.083642961711462,
          "ci_hi": 10.112351095682751
        },
        {
          "event_time": -4,
          "att": -2.4863636363636354,
          "se": 7.226080244627205,
          "ci_lo": -16.649480915832957,
          "ci_hi": 11.676753643105688
        },
        {
          "event_time": -3,
          "att": -8.62396694214876,
          "se": 6.117828400750187,
          "ci_lo": -20.614910607619127,
          "ci_hi": 3.3669767233216064
        },
        {
          "event_time": -2,
          "att": 3.484189723320157,
          "se": 6.699394184315834,
          "ci_lo": -9.64662287793888,
          "ci_hi": 16.615002324579194
        },
        {
          "event_time": -1,
          "att": 0.0,
          "se": 0.0,
          "ci_lo": 0.0,
          "ci_hi": 0.0
        },
        {
          "event_time": 0,
          "att": 14.124505928853758,
          "se": 6.257137682469371,
          "ci_lo": 1.860516071213791,
          "ci_hi": 26.388495786493724
        },
        {
          "event_time": 1,
          "att": 13.341897233201577,
          "se": 5.413439408862013,
          "ci_lo": 2.731555991832032,
          "ci_hi": 23.95223847457112
        },
        {
          "event_time": 2,
          "att": 7.250988142292489,
          "se": 6.120384180621005,
          "ci_lo": -4.7449648517246805,
          "ci_hi": 19.24694113630966
        },
        {
          "event_time": 3,
          "att": 9.982213438735174,
          "se": 6.763391945411589,
          "ci_lo": -3.2740347742715414,
          "ci_hi": 23.23846165174189
        },
        {
          "event_time": 4,
          "att": 15.90513833992095,
          "se": 6.40797323409877,
          "ci_lo": 3.345510801087361,
          "ci_hi": 28.464765878754537
        },
        {
          "event_time": 5,
          "att": 22.04545454545454,
          "se": 7.394838913361307,
          "ci_lo": 7.5515702752663785,
          "ci_hi": 36.5393388156427
        },
        {
          "event_time": 6,
          "att": 33.43083003952569,
          "se": 8.775327727929529,
          "ci_lo": 16.231187692783813,
          "ci_hi": 50.63047238626756
        },
        {
          "event_time": 7,
          "att": 28.359683794466402,
          "se": 7.830791171576355,
          "ci_lo": 13.011333098176745,
          "ci_hi": 43.70803449075606
        },
        {
          "event_time": 8,
          "att": 29.059288537549403,
          "se": 8.7669394383735,
          "ci_lo": 11.876087238337345,
          "ci_hi": 46.242489836761465
        },
        {
          "event_time": 9,
          "att": 29.733201581027664,
          "se": 10.102119730526045,
          "ci_lo": 9.933046909196616,
          "ci_hi": 49.53335625285871
        },
        {
          "event_time": 10,
          "att": 24.98966942148759,
          "se": 10.175381659487144,
          "ci_lo": 5.045921368892788,
          "ci_hi": 44.93341747408239
        },
        {
          "event_time": 11,
          "att": 35.54545454545455,
          "se": 8.825202035421931,
          "ci_lo": 18.248058556027562,
          "ci_hi": 52.842850534881535
        },
        {
          "event_time": 12,
          "att": 32.83549783549783,
          "se": 10.137062976683122,
          "ci_lo": 12.966854401198916,
          "ci_hi": 52.70414126979675
        },
        {
          "event_time": 13,
          "att": 37.25324675324674,
          "se": 8.795063660684198,
          "ci_lo": 20.014921978305715,
          "ci_hi": 54.49157152818777
        },
        {
          "event_time": 14,
          "att": 45.396103896103895,
          "se": 9.241877021696203,
          "ci_lo": 27.28202493357934,
          "ci_hi": 63.510182858628454
        },
        {
          "event_time": 15,
          "att": 43.186868686868685,
          "se": 8.316298164011833,
          "ci_lo": 26.88692428540549,
          "ci_hi": 59.48681308833188
        },
        {
          "event_time": 16,
          "att": 31.641711229946516,
          "se": 10.694159418925405,
          "ci_lo": 10.681158768852722,
          "ci_hi": 52.60226369104031
        },
        {
          "event_time": 17,
          "att": 47.60227272727273,
          "se": 10.354124052177786,
          "ci_lo": 27.308189585004268,
          "ci_hi": 67.89635586954118
        },
        {
          "event_time": 18,
          "att": 43.13636363636363,
          "se": 11.719590489731448,
          "ci_lo": 20.165966276489996,
          "ci_hi": 66.10676099623727
        }
      ]
    },
    "web講演会": {
      "att": 32.32350332594235,
      "se": 4.383954463243972,
      "p": 1.667554982986985e-13,
      "ci_lo": 23.730952577984162,
      "ci_hi": 40.91605407390053,
      "sig": "***",
      "n_treated": 30,
      "dynamic": [
        {
          "event_time": -6,
          "att": -19.094405594405597,
          "se": 5.313816141575475,
          "ci_lo": -29.509485231893528,
          "ci_hi": -8.679325956917666
        },
        {
          "event_time": -5,
          "att": -11.979020979020978,
          "se": 6.01298082395144,
          "ci_lo": -23.7644633939658,
          "ci_hi": -0.19357856407615515
        },
        {
          "event_time": -4,
          "att": -13.144781144781145,
          "se": 5.0378558588469184,
          "ci_lo": -23.018978628121104,
          "ci_hi": -3.2705836614411847
        },
        {
          "event_time": -3,
          "att": -7.96865203761756,
          "se": 5.317121421467117,
          "ci_lo": -18.39021002369311,
          "ci_hi": 2.45290594845799
        },
        {
          "event_time": -2,
          "att": -5.289393939393941,
          "se": 4.891677920003388,
          "ci_lo": -14.87708266260058,
          "ci_hi": 4.298294783812699
        },
        {
          "event_time": -1,
          "att": 0.0,
          "se": 0.0,
          "ci_lo": 0.0,
          "ci_hi": 0.0
        },
        {
          "event_time": 0,
          "att": 26.33787878787879,
          "se": 4.84019511555655,
          "ci_lo": 16.851096361387953,
          "ci_hi": 35.82466121436963
        },
        {
          "event_time": 1,
          "att": 25.381818181818176,
          "se": 5.38249659547699,
          "ci_lo": 14.832124854683276,
          "ci_hi": 35.93151150895308
        },
        {
          "event_time": 2,
          "att": 26.88939393939394,
          "se": 5.114416527041506,
          "ci_lo": 16.86513754639259,
          "ci_hi": 36.91365033239529
        },
        {
          "event_time": 3,
          "att": 30.392424242424234,
          "se": 4.825038483505542,
          "ci_lo": 20.935348814753368,
          "ci_hi": 39.8494996700951
        },
        {
          "event_time": 4,
          "att": 23.56363636363636,
          "se": 3.802214747032682,
          "ci_lo": 16.1112954594523,
          "ci_hi": 31.015977267820418
        },
        {
          "event_time": 5,
          "att": 26.689393939393938,
          "se": 5.5759727680806055,
          "ci_lo": 15.76048731395595,
          "ci_hi": 37.61830056483193
        },
        {
          "event_time": 6,
          "att": 26.289393939393943,
          "se": 7.535862206637594,
          "ci_lo": 11.51910401438426,
          "ci_hi": 41.059683864403624
        },
        {
          "event_time": 7,
          "att": 31.316558441558435,
          "se": 4.831873510086812,
          "ci_lo": 21.846086361788284,
          "ci_hi": 40.78703052132859
        },
        {
          "event_time": 8,
          "att": 32.576298701298704,
          "se": 6.348464003416387,
          "ci_lo": 20.133309254602587,
          "ci_hi": 45.01928814799482
        },
        {
          "event_time": 9,
          "att": 29.48148148148148,
          "se": 6.457632810684984,
          "ci_lo": 16.824521172538912,
          "ci_hi": 42.138441790424054
        },
        {
          "event_time": 10,
          "att": 36.74410774410773,
          "se": 7.104858259327944,
          "ci_lo": 22.81858555582496,
          "ci_hi": 50.6696299323905
        },
        {
          "event_time": 11,
          "att": 28.890572390572384,
          "se": 6.335690840748132,
          "ci_lo": 16.472618342706046,
          "ci_hi": 41.30852643843872
        },
        {
          "event_time": 12,
          "att": 41.59090909090907,
          "se": 6.3981658806521695,
          "ci_lo": 29.05050396483082,
          "ci_hi": 54.13131421698732
        },
        {
          "event_time": 13,
          "att": 41.498316498316484,
          "se": 7.316873532245167,
          "ci_lo": 27.15724437511596,
          "ci_hi": 55.83938862151701
        },
        {
          "event_time": 14,
          "att": 40.51636363636363,
          "se": 8.220644458968472,
          "ci_lo": 24.403900496785422,
          "ci_hi": 56.62882677594183
        },
        {
          "event_time": 15,
          "att": 45.06727272727272,
          "se": 6.499554272429478,
          "ci_lo": 32.32814635331095,
          "ci_hi": 57.8063991012345
        },
        {
          "event_time": 16,
          "att": 32.816287878787875,
          "se": 6.291805592475883,
          "ci_lo": 20.484348917535144,
          "ci_hi": 45.14822684004061
        },
        {
          "event_time": 17,
          "att": 40.318181818181806,
          "se": 6.143703875511127,
          "ci_lo": 28.27652222218,
          "ci_hi": 52.35984141418361
        },
        {
          "event_time": 18,
          "att": 37.13636363636362,
          "se": 8.12322517919496,
          "ci_lo": 21.214842285141494,
          "ci_hi": 53.057884987585744
        }
      ]
    }
  },
  "cohort_distribution": {
    "2023-06": 3,
    "2023-07": 4,
    "2023-08": 4,
    "2023-09": 4,
    "2023-10": 1,
    "2023-11": 4,
    "2023-12": 1,
    "2024-01": 1,
    "2024-03": 3,
    "2024-04": 5,
    "2024-05": 3,
    "2024-06": 1,
    "2024-08": 3,
    "2024-09": 2,
    "2024-11": 1,
    "2025-01": 1
  },
  "descriptive_stats": {
    "control": {
      "count": 726,
      "mean": 123.39669421487604,
      "std": 27.880774541908117
    },
    "treated": {
      "count": 1353,
      "mean": 141.42719881744273,
      "std": 46.07060666128349
    }
  },
  "n_treated": 41,
  "n_control": 22,
  "n_total": 63
}